{
    "file": "../google/golden/23.html",
    "components": [
        {
            "type": "SEARCH_RESULT",
            "alignment": "LEFT",
            "page_url": "/url?q=https://petersburgedu.ru/dnevnik/&sa=U&ved=0ahUKEwjGg8rbro_XAhVBSZoKHT2sCJEQFggUMAA&usg=AOvVaw1CI7LE-gK3HabhiMjtMObh",
            "title": "Электронный дневник - Санкт-Петербург - Портал ...",
            "snippet": "Ведение Электронного дневника и электронного журнала является \nгосударственной услугой Санкт-Петербурга, обеспечивающей оперативное,\n ...",
            "view_url": "https://petersburgedu.ru/dnevnik/"
        },
        {
            "type": "SEARCH_RESULT",
            "alignment": "LEFT",
            "page_url": "/url?q=http://sgo.centerstart.ru/&sa=U&ved=0ahUKEwjGg8rbro_XAhVBSZoKHT2sCJEQFggaMAE&usg=AOvVaw30YlAuR2f6hJJ8_UOQTzVm",
            "title": "Сетевой Город. Образование - Краснодар",
            "snippet": "Образовательная организация; Управление образования. Страна. \nВыберите страну... Россия. Регион. Выберите регион... Краснодарский край.",
            "view_url": "sgo.centerstart.ru/"
        },
        {
            "type": "SEARCH_RESULT",
            "alignment": "LEFT",
            "page_url": "/url?q=https://cabinet.ruobr.ru/&sa=U&ved=0ahUKEwjGg8rbro_XAhVBSZoKHT2sCJEQFgggMAI&usg=AOvVaw1tQ1uaczMbsERAAseeOO8c",
            "title": "Личный кабинет граждан Кемеровской области",
            "snippet": "Регистрация. В целях упрощения процедур идентификации и \nаутентификации граждан для получения государственных услуг в \nэлектронном виде ...",
            "view_url": "https://cabinet.ruobr.ru/"
        },
        {
            "type": "SEARCH_RESULT",
            "alignment": "LEFT",
            "page_url": "/url?q=https://web2edu.ru/&sa=U&ved=0ahUKEwjGg8rbro_XAhVBSZoKHT2sCJEQFggmMAM&usg=AOvVaw3-S6Yx84wChhzKlbb0y6bM",
            "title": "Образование (веб 2.0) - Пермь",
            "snippet": "Дневники и журналы ... в электронных правительствах регионов РФ .... \nпредоставления услуги \"Электронный дневник\" за 1-4 октября 2017 года!",
            "view_url": "https://web2edu.ru/"
        },
        {
            "type": "SEARCH_RESULT",
            "alignment": "LEFT",
            "page_url": "/url?q=https://school.mosreg.ru/&sa=U&ved=0ahUKEwjGg8rbro_XAhVBSZoKHT2sCJEQFggsMAQ&usg=AOvVaw3ClD0IiqUtmxMHhNyyfgzk",
            "title": "«Школьный портал»",
            "snippet": "Вход в электронный дневник. Войти Восстановить ... Школьный портал \nпредоставляет доступ к ряду государственных услуг в электронном виде. \nПортал ...",
            "view_url": "https://school.mosreg.ru/"
        },
        {
            "type": "SEARCH_RESULT",
            "alignment": "LEFT",
            "page_url": "/url?q=https://www.mos.ru/pgu/ru/services/link/2103&sa=U&ved=0ahUKEwjGg8rbro_XAhVBSZoKHT2sCJEQFggyMAU&usg=AOvVaw1JlYsidQOMN2ls1En2wakn",
            "title": "Электронный дневник - Москва - Официальный сайт Мэра Москвы",
            "snippet": "Госуслуги Москвы. Электронный дневник школьника позволяет \nконтролировать успеваемость в школе, отслеживать выполнение учебной \nнагрузки.",
            "view_url": "https://www.mos.ru/pgu/ru/services/link/2103"
        },
        {
            "type": "SEARCH_RESULT",
            "alignment": "LEFT",
            "page_url": "/url?q=https://edu.brsc.ru/&sa=U&ved=0ahUKEwjGg8rbro_XAhVBSZoKHT2sCJEQFgg3MAY&usg=AOvVaw2GipbG8xmDZksyPj8m5Qif",
            "title": "АИС «Образование",
            "snippet": "ведение электронного журнала успеваемости;; ведение электронного \nдневника учащегося;; обеспечение автоматизированного учета питания ...",
            "view_url": "https://edu.brsc.ru/"
        },
        {
            "type": "SEARCH_RESULT",
            "alignment": "LEFT",
            "page_url": "/url?q=http://one.pskovedu.ru/&sa=U&ved=0ahUKEwjGg8rbro_XAhVBSZoKHT2sCJEQFgg9MAc&usg=AOvVaw2kCUDtq1Xh2l7htJ_9Dcqb",
            "title": "Электронный журнал - Псков - Pskovedu.ru",
            "snippet": "Электронные журналы и дневники Псковской области.",
            "view_url": "one.pskovedu.ru/"
        },
        {
            "type": "SEARCH_RESULT",
            "alignment": "LEFT",
            "page_url": "/url?q=https://school17-kt.eljur.ru/&sa=U&ved=0ahUKEwjGg8rbro_XAhVBSZoKHT2sCJEQFghDMAg&usg=AOvVaw37OPtK5FtgX0QcEA0NUG_7",
            "title": "Электронный журнал — МАОУ «СОШ № 17» — Краснотурьинск",
            "snippet": "Электронный журнал. Объявления. 26 октября, Четверг. МАОУ «СОШ № 17» \n... Вход в журнал. Логин: Пароль: Ввести пригласительный код Забыли ...",
            "view_url": "https://school17-kt.eljur.ru/"
        },
        {
            "type": "SEARCH_RESULT",
            "alignment": "LEFT",
            "page_url": "/url?q=https://es.ciur.ru/&sa=U&ved=0ahUKEwjGg8rbro_XAhVBSZoKHT2sCJEQFghJMAk&usg=AOvVaw2Eg4OL5KVtIg7gegYAq6pK",
            "title": "БАРС.Web-Образование",
            "snippet": "Электронная школа.",
            "view_url": "https://es.ciur.ru/"
        }
    ]
}